pds/ingress/VERSION.txt
pds/ingress/__init__.py
pds/ingress/conf.default.ini
pds/ingress/authorizer/README.md
pds/ingress/authorizer/index.js
pds/ingress/authorizer/package-lock.json
pds/ingress/authorizer/package.json
pds/ingress/client/abort_multipart_uploads.py
pds/ingress/client/pds_ingress_client.py
pds/ingress/client/pds_status_client.py
pds/ingress/service/pds_ingress_app.py
pds/ingress/service/pds_status_app.py
pds/ingress/service/sync_s3_metadata.py
pds/ingress/service/config/VERSION.txt
pds/ingress/service/config/bucket-map.schema
pds/ingress/service/config/bucket-map.yaml.tmpl
pds/ingress/service/util/auth_util.py
pds/ingress/service/util/backoff_util.py
pds/ingress/service/util/config_util.py
pds/ingress/service/util/hash_util.py
pds/ingress/service/util/log_util.py
pds/ingress/service/util/node_util.py
pds/ingress/service/util/path_util.py
pds/ingress/service/util/progress_util.py
pds/ingress/service/util/report_util.py
pds/ingress/util/auth_util.py
pds/ingress/util/backoff_util.py
pds/ingress/util/config_util.py
pds/ingress/util/hash_util.py
pds/ingress/util/log_util.py
pds/ingress/util/node_util.py
pds/ingress/util/path_util.py
pds/ingress/util/progress_util.py
pds/ingress/util/report_util.py
pds_data_upload_manager-2.3.0.dist-info/licenses/LICENSE.md
pds_data_upload_manager-2.3.0.dist-info/licenses/NOTICE.txt
pds_data_upload_manager-2.3.0.dist-info/METADATA
pds_data_upload_manager-2.3.0.dist-info/WHEEL
pds_data_upload_manager-2.3.0.dist-info/entry_points.txt
pds_data_upload_manager-2.3.0.dist-info/top_level.txt
pds_data_upload_manager-2.3.0.dist-info/zip-safe
pds_data_upload_manager-2.3.0.dist-info/RECORD
