Metadata-Version: 2.4
Name: pds-data-upload-manager
Version: 2.3.0
Summary: Planetary Data Service Data Delivery Manager
Home-page: https://github.com/NASA-PDS/data-upload-manager
Download-URL: https://github.com/NASA-PDS/data-upload-manager/releases/
Author: PDS
Author-email: pds_operator@jpl.nasa.gov
License: apache-2.0
Keywords: pds,planetary data,aws,s3,ingress,data upload
Classifier: Programming Language :: Python :: 3
Classifier: Programming Language :: Python :: 3.12
Classifier: Programming Language :: Python :: 3.13
Classifier: Operating System :: OS Independent
Requires-Python: >=3.12
License-File: LICENSE.md
License-File: NOTICE.txt
Requires-Dist: backoff~=2.2.1
Requires-Dist: boto3~=1.25
Requires-Dist: boto3-stubs[apigateway,cognito,essential]~=1.25
Requires-Dist: more-itertools<10.9,>=9.0
Requires-Dist: joblib<1.6.0,>=1.3.1
Requires-Dist: requests~=2.23
Requires-Dist: requests-mock~=1.12.1
Requires-Dist: types-requests~=2.23
Requires-Dist: PyYAML~=6.0
Requires-Dist: setuptools<80.10.0,>=75.8.1
Requires-Dist: tqdm~=4.67.0
Requires-Dist: types-PyYAML~=6.0
Requires-Dist: yamale~=6.0.0
Provides-Extra: dev
Requires-Dist: awscli-local~=0.22.0; extra == "dev"
Requires-Dist: black~=23.7; extra == "dev"
Requires-Dist: coverage<7.12,>=7.3; extra == "dev"
Requires-Dist: flake8<7.4,>=7.1.1; extra == "dev"
Requires-Dist: flake8-bugbear<24.13.0,>=23.7.10; extra == "dev"
Requires-Dist: flake8-docstrings~=1.7.0; extra == "dev"
Requires-Dist: flake8-import-order<0.20.0,>=0.18.2; extra == "dev"
Requires-Dist: localstack-client~=2.5; extra == "dev"
Requires-Dist: mypy<1.19.0,>=1.5.1; extra == "dev"
Requires-Dist: pep8-naming<0.16.0,>=0.13.3; extra == "dev"
Requires-Dist: pydocstyle~=6.3.0; extra == "dev"
Requires-Dist: pytest<8.5,>=7.4; extra == "dev"
Requires-Dist: pytest-cov<7.1,>=4.1; extra == "dev"
Requires-Dist: pytest-watch~=4.2.0; extra == "dev"
Requires-Dist: pytest-xdist<3.9.0,>=3.3.1; extra == "dev"
Requires-Dist: pre-commit<4.4.0,>=3.3.3; extra == "dev"
Requires-Dist: sphinx<8.3.0,>=7.2.6; extra == "dev"
Requires-Dist: sphinx-rtd-theme<3.1,>=2.0; extra == "dev"
Requires-Dist: sphinx-argparse~=0.5.2; extra == "dev"
Requires-Dist: terraform-local<0.25.0,>=0.18.2; extra == "dev"
Requires-Dist: tox<4.32,>=4.11; extra == "dev"
Requires-Dist: types-setuptools<80.9.1,>=68.1.0; extra == "dev"
Requires-Dist: Jinja2<3.2; extra == "dev"
Dynamic: download-url
Dynamic: license-file
